MANIFEST.in
README.md
setup.py
scapy_packet_viewer/__init__.py
scapy_packet_viewer/button_bar.py
scapy_packet_viewer/column_configuration.py
scapy_packet_viewer/details_view.py
scapy_packet_viewer/edit_view.py
scapy_packet_viewer/extended_edit.py
scapy_packet_viewer/extended_listbox.py
scapy_packet_viewer/main_window.py
scapy_packet_viewer/packet_list_view.py
scapy_packet_viewer/pop_ups.py
scapy_packet_viewer/project.py
scapy_packet_viewer/py.typed
scapy_packet_viewer/row_formatter.py
scapy_packet_viewer/version.py
scapy_packet_viewer/viewer.py
scapy_packet_viewer.egg-info/PKG-INFO
scapy_packet_viewer.egg-info/SOURCES.txt
scapy_packet_viewer.egg-info/dependency_links.txt
scapy_packet_viewer.egg-info/not-zip-safe
scapy_packet_viewer.egg-info/requires.txt
scapy_packet_viewer.egg-info/top_level.txt
scapy_packet_viewer/custom_views/__init__.py
scapy_packet_viewer/custom_views/analyze_can_view/__init__.py
scapy_packet_viewer/custom_views/analyze_can_view/analyze_can_view.py
scapy_packet_viewer/custom_views/analyze_can_view/decimal_edit.py
scapy_packet_viewer/custom_views/analyze_can_view/graph_tabs.py
scapy_packet_viewer/custom_views/analyze_can_view/graphs.py
scapy_packet_viewer/custom_views/analyze_can_view/message_layout_string.py
scapy_packet_viewer/custom_views/analyze_can_view/signal_table.py
scapy_packet_viewer/custom_views/analyze_can_view/utils.py