Metadata-Version: 2.1
Name: scapy-packet-viewer
Version: 0.0.1
Summary: Packet viewer for SecDev's Scapy.
Home-page: https://github.com/TH-eMundo/scapy-packet_viewer
Author: Andreas Korb, Nils Weiss, Tabea Spahn, Tim Henkes
Author-email: todo@e-mundo.de
License: GPLv2
Platform: UNKNOWN
Classifier: Intended Audience :: Developers
Classifier: Intended Audience :: Education
Classifier: Intended Audience :: Information Technology
Classifier: Intended Audience :: Science/Research
Classifier: License :: OSI Approved :: GNU General Public License v2 (GPLv2)
Classifier: Programming Language :: Python :: 3
Classifier: Programming Language :: Python :: 3 :: Only
Classifier: Programming Language :: Python :: 3.6
Classifier: Programming Language :: Python :: 3.7
Classifier: Programming Language :: Python :: 3.8
Classifier: Programming Language :: Python :: 3.9
Classifier: Typing :: Typed
Classifier: Topic :: Scientific/Engineering
Classifier: Topic :: Security
Classifier: Development Status :: 3 - Alpha
Requires-Python: >=3.6
Provides-Extra: full
